[
  {
    "id": 176,
    "question": "учить — научить",
    "options": [
      "阅读、朗读",
      "教、教育",
      "学习、研究",
      "记住、背诵"
    ],
    "correctAnswer": 1,
    "explanation": ""
  },
  {
    "id": 177,
    "question": "обучать — обучить",
    "options": [
      "教会、训练",
      "教育、培养",
      "指导、辅导",
      "学习、研究"
    ],
    "correctAnswer": 0,
    "explanation": ""
  },
  {
    "id": 178,
    "question": "приучать — приучить",
    "options": [
      "使……养成习惯",
      "使……加快速度",
      "使……感到惊讶",
      "使……失去兴趣"
    ],
    "correctAnswer": 0,
    "explanation": ""
  }
]